asos_curl/__init__.py
asos_curl/plugin.py
asos_curl-1.0.4.dist-info/LICENSE
asos_curl-1.0.4.dist-info/METADATA
asos_curl-1.0.4.dist-info/WHEEL
asos_curl-1.0.4.dist-info/top_level.txt
asos_curl-1.0.4.dist-info/RECORD
